android_sdk_updater-1.0.1.data/scripts/android-sdk-updater
android_sdk_updater-1.0.1.dist-info/DESCRIPTION.rst
android_sdk_updater-1.0.1.dist-info/METADATA
android_sdk_updater-1.0.1.dist-info/RECORD
android_sdk_updater-1.0.1.dist-info/WHEEL
android_sdk_updater-1.0.1.dist-info/metadata.json
android_sdk_updater-1.0.1.dist-info/top_level.txt
sdk_updater/__init__.py
sdk_updater/list.py
sdk_updater/package.py
sdk_updater/scan.py
sdk_updater/update.py
