Metadata-Version: 2.0
Name: android-sdk-updater
Version: 1.0.1
Summary: A command-line utility for keeping your Android dependencies up-to-date.
Home-page: https://github.com/tadfisher/android-sdk-updater
Author: Tad Fisher
Author-email: tadfisher@gmail.com
License: Copyright 2016 Tad Fisher
Requires-Dist: jprops
Requires-Dist: pexpect
Requires-Dist: semantic-version
